Workbook
Name PL_switch: Analysis!$E$21
Name F_Switch1: Analysis!$F$38
Name F_List: Analysis!$D$25:$D$36
Name Scenario: Scenarios!$D$11
Name PL_Metrics: Analysis!$D$11:$D$19
Name S_Switch: Scenarios!$E$12
Name Div: Guide!$F$53
Name S_Case: Guide!$D$56:$D$59
Name Currency: Guide!$F$36
Name F_Switch2: Analysis!$F$39

Sheet Cover
C13: =Guide!F34 -> Distributor
C14: =Guide!F35 -> USA
B15: Financial Forecast for a period of 5 Year
B16: ="Model Objective: "&Guide!F42 -> Model Objective: To raise Funding

Sheet Guide
B2: Model Cell Style
C3: this section provide guide to what the value in the represent
D4: Description | F4: Sample | H4: note
D5: Input cell style | F5: 12345 | H5: values in this style represent hardcoded value and can be changed
D6: Linked cell style | F6: 12345 | H6: values in this style are linked from another worksheet or another cell
D7: Formula cell style | F7: 12345 | H7: contain formulas and should not be tampared with
D8: Percentage cell style | F8: 0.055 | H8: represent values in their hundred of unit
D9: Multiple cell style | F9: 5.5 | H9: represent values in their multiples of unit
D10: Subtotal cells | F10: 12345 | H10: calculations of sub group of rows or columns
D11: Total cells | F11: 12345 | H11: calculation of entire rows or column
D12: Banner style | F12: Title | H12: table ending
D13: Heading 1 | F13: Title | H13: section title
D14: Heading 2 | F14: Title | H14: sub-section title
B17: Model Content
C18: description of the model table of content
D19: Description | F19: cell color
D20: Model Summary | H20: overview of the model output
D21: Inputs/Assumption | H21: model drivers and raw data input
D22: Calculations | H22: engine room where calculations were done
D24: Profit or Loss Account | H24: revenue, expenses and profit result
D25: Balance Sheet | H25: business sources of funds and use of funds
D26: Cashflow Statement | H26: analysis of the business inflow and outflow
D28: Analysis | H28: investment viability measurement
B31: Model Detail
C32: this section list the information of the model
D33: Company Name | F33: TOWV Bootcamp Limited
D34: Business Industry | F34: Distributor
D35: Business Location | F35: USA
D36: Business currency | F36: $
D37: Contact us: email
D38: Contact us: phone number
D39: Model start period | F39: 44562
D40: Model forecast period | F40: 5
D41: Month in a period | F41: 12
D42: Model Objective | F42: To raise Funding
B45: Glossary
C46: explanation of abbreviated models in the model
D47: Abbreviation | F47: Full meaning
D48: Calc | F48: Calculations
D49: PL | F49: Profit or Loss Account
D50: BS | F50: Balance sheet
D51: CF | F51: Cashflow statement
D52: DCF | F52: Discounted cashflow
D53: Million division | F53: 1000
D55: Scenarios
D56: Base Case
D57: Conservative Case
D58: Best Case
D59: Worse Case
D61: Name Manager
D62: Currency | E62: =Guide!$F$37
D63: Div | E63: =Guide!$F$54
D64: F_List | E64: =Analysis!$D$25:$D$36
D65: F_Switch1 | E65: =Analysis!$F$38
D66: F_Switch2 | E66: =Analysis!$F$39
D67: PL_Metrics | E67: =Analysis!$D$11:$D$19
D68: PL_switch | E68: =Analysis!$E$21
D69: Print_Titles | E69: =Guide!$1:$1
D70: S_Case | E70: =Guide!$D$57:$D$60
D71: S_Switch | E71: =Scenarios!$E$12

Sheet Summary
B2: =Guide!$F$33 -> TOWV Bootcamp Limited
B3: Summary/Dashboard
L7: =Inputs!L6 -> 2022 | M7: =Inputs!M6 -> 2023 | N7: =Inputs!N6 -> 2024 | O7: =Inputs!O6 -> 2025 | P7: =Inputs!P6 -> 2026
J8: =Analysis!D38 -> Revenue | L8: =Analysis!L38 -> 901.2 | M8: =Analysis!M38 -> 941.754 | N8: =Analysis!N38 -> 993.55047 | O8: =Analysis!O38 -> 1093.4023 | P8: =Analysis!P38 -> 1120.7374
J9: growth | L9: 0 | M9: =M8/L8-1 -> 0.045 | N9: =N8/M8-1 -> 0.055 | O9: =O8/N8-1 -> 0.1005 | P9: =P8/O8-1 -> 0.025
J10: =Analysis!D39 -> EBITDA | L10: =Analysis!L39 -> 132.37 | M10: =Analysis!M39 -> 181.36204 | N10: =Analysis!N39 -> 185.66039 | O10: =Analysis!O39 -> 198.75786 | P10: =Analysis!P39 -> 185.29815
J11: margin | L11: =L10/L8 -> 0.14688194 | M11: =M10/M8 -> 0.192579 | N11: =N10/N8 -> 0.18686558 | O11: =O10/O8 -> 0.18177926 | P11: =P10/P8 -> 0.16533593

Sheet Inputs
B2: =Guide!$F$33 -> TOWV Bootcamp Limited
B3: Inputs & Assumptions
G4: period start | L4: =K5+1 -> 44562 | M4: =L5+1 -> 44927 | N4: =M5+1 -> 45292 | O4: =N5+1 -> 45658 | P4: =O5+1 -> 46023
C5: =Scenario -> Live Scenario: Base Case | G5: Period end | K5: =Guide!F39-1 -> 44561 | L5: =EDATE(K5,Guide!$F$41) -> 44926 | M5: =EDATE(L5,Guide!$F$41) -> 45291 | N5: =EDATE(M5,Guide!$F$41) -> 45657 | O5: =EDATE(N5,Guide!$F$41) -> 46022 | P5: =EDATE(O5,Guide!$F$41) -> 46387
C6: Model balance check | G6: Years | L6: =YEAR(L4) -> 2022 | M6: =YEAR(M4) -> 2023 | N6: =YEAR(N4) -> 2024 | O6: =YEAR(O4) -> 2025 | P6: =YEAR(P4) -> 2026
D7: Descriptions | E7: unit | F7: Inputs/Linked | G7: Row Aver. | H7: Row Total
B9: General & Macro-Economic Assumptions
C10: Timing
D11: Period | L11: =K11+1 -> 1 | M11: =L11+1 -> 2 | N11: =M11+1 -> 3 | O11: =N11+1 -> 4 | P11: =O11+1 -> 5
D12: Days in a period | E12: days | L12: =L5-K5 -> 365 | M12: =M5-L5 -> 365 | N12: =N5-M5 -> 366 | O12: =O5-N5 -> 365 | P12: =P5-O5 -> 365
D13: Month in a period | E13: month | L13: =DATEDIF(K5,L5,"m") -> 12 | M13: =DATEDIF(L5,M5,"m") -> 12 | N13: =DATEDIF(M5,N5,"m") -> 12 | O13: =DATEDIF(N5,O5,"m") -> 12 | P13: =DATEDIF(O5,P5,"m") -> 12
C15: Macro-Econmic Assumptions
D16: Inflation Rate
D17: Inflation rate | E17: %age | F17: change from the scenario worksheet | L17: =Scenarios!L18 -> 0 | M17: =Scenarios!M18 -> 0.025 | N17: =Scenarios!N18 -> 0.0245 | O17: =Scenarios!O18 -> 0.0237 | P17: =Scenarios!P18 -> 0.0225
D18: Inflation factor | E18: times | L18: =(1+L17)^(L11-1) -> 1 | M18: =(1+M17)^(M11-1) -> 1.025 | N18: =(1+N17)^(N11-1) -> 1.0496002 | O18: =(1+O17)^(O11-1) -> 1.0727984 | P18: =(1+P17)^(P11-1) -> 1.0930833
D20: Pricing growth rate
D21: Product pricing growth | E21: %age | L21: 0 | M21: 0 | N21: 0 | O21: 0 | P21: 0
D23: Quantity growth rate | F23: change from the scenario worksheet
D24: Volume growth rate (CAGR) | E24: %age | F24: 0.045 | L24: =Scenarios!L25 -> 0 | M24: =Scenarios!M25 -> 0.045 | N24: =Scenarios!N25 -> 0.055 | O24: =Scenarios!O25 -> 0.1005 | P24: =Scenarios!P25 -> 0.025
D26: Government
D27: Provision for tax | E27: %age | L27: 0.21 | M27: 0.21 | N27: 0.21 | O27: 0.21 | P27: 0.21
D29: Use of Assets
D30: Maintenable capex | E30: factor of dep. | L30: 1 | M30: 1.025 | N30: 1.0496002 | O30: 1.0727984 | P30: 1.0930833
B32: Financing & Use of Funds
C33: Funding
D34: Loan Financing
D35: Long term loan | E35: =Currency -> $ | L35: 100000 | M35: 0 | N35: 0 | O35: 0 | P35: 0
D36: Equity Financing
D37: Equity | E37: =Currency -> $ | L37: 150000 | M37: 0 | N37: 0 | O37: 0 | P37: 0
D38: Total Funding | E38: =Currency -> $ | G38: =SUM(L38:P38)/Div -> 250 | L38: =L35+L37 -> 250000 | M38: =M35+M37 -> 0 | N38: =N35+N37 -> 0 | O38: =O35+O37 -> 0 | P38: =P35+P37 -> 0
C40: Cost of Financing
D41: Loans
D42: Loan period | E42: years | F42: 4
D43: Loan interest rate | E43: %age | L43: 0.0716 | M43: 0.0716 | N43: 0.0716 | O43: 0.0716 | P43: 0.0716
D45: Equity
D46: Dividend payout ratio | E46: %age | L46: 0.3 | M46: 0.3 | N46: 0.3 | O46: 0.3 | P46: 0.3
C48: Use of Funds
D49: Business registration & Licensing | F49: Lifespan
D50: Business registration | E50: =Currency -> $ | L50: 1500 | M50: 0 | N50: 0 | O50: 0 | P50: 0
D51: Licensing | E51: =Currency -> $ | L51: 1500 | M51: 0 | N51: 0 | O51: 0 | P51: 0
D52: Professional cost | E52: =Currency -> $ | L52: 3000 | M52: 0 | N52: 0 | O52: 0 | P52: 0
D53: Research | E53: =Currency -> $ | L53: 2500 | M53: 0 | N53: 0 | O53: 0 | P53: 0
D54: Assets
D55: Furnitures & Fittings | E55: =Currency -> $ | F55: 5 | L55: 25000 | M55: 0 | N55: 0 | O55: 0 | P55: 0
D56: Plant & Equipment | E56: =Currency -> $ | F56: 5 | L56: 15000 | M56: 0 | N56: 0 | O56: 0 | P56: 0
D57: Website & Software | E57: =Currency -> $ | F57: 5 | L57: 3000 | M57: 0 | N57: 0 | O57: 0 | P57: 0
D58: Vehicles | E58: =Currency -> $ | F58: 5 | L58: 10000 | M58: 0 | N58: 0 | O58: 0 | P58: 0
D59: Inventory
D60: Stock product | E60: =Currency -> $ | L60: 75000 | M60: 0 | N60: 0 | O60: 0 | P60: 0
D61: Awareness
D62: Marketing & Advertising | E62: =Currency -> $ | L62: 30000 | M62: 0 | N62: 0 | O62: 0 | P62: 0
D63: PRO | E63: =Currency -> $ | L63: 10000 | M63: 0 | N63: 0 | O63: 0 | P63: 0
D64: Prepaid Expenses
D65: Rent | E65: =Currency -> $ | L65: 15000 | M65: 0 | N65: 0 | O65: 0 | P65: 0
D66: Insurance | E66: =Currency -> $ | L66: 5000 | M66: 0 | N66: 0 | O66: 0 | P66: 0
D67: Provision for opex (WC) | E67: =Currency -> $ | L67: =L38-SUM(L50:L66) -> 53500 | M67: =M38-SUM(M50:M66) -> 0 | N67: =N38-SUM(N50:N66) -> 0 | O67: =O38-SUM(O50:O66) -> 0 | P67: =P38-SUM(P50:P66) -> 0
D68: Total use of funds | E68: =Currency -> $ | L68: =SUM(L50:L67) -> 250000 | M68: =SUM(M50:M67) -> 0 | N68: =SUM(N50:N67) -> 0 | O68: =SUM(O50:O67) -> 0 | P68: =SUM(P50:P67) -> 0
B71: Working Capital & Operational Cost
C72: Operating Working Capital
D73: Assets
D74: Inventories | E74: days | L74: 40 | M74: 40 | N74: 40 | O74: 40 | P74: 40
D75: Trade receivables | E75: days | L75: 25 | M75: 25 | N75: 25 | O75: 25 | P75: 25
D76: Prepayment | E76: days | L76: 30 | M76: 30 | N76: 30 | O76: 30 | P76: 30
D78: Liabilities
D79: Trade payables | E79: days | L79: 30 | M79: 30 | N79: 30 | O79: 30 | P79: 30
D80: Accrued expenses | E80: days | L80: 25 | M80: 25 | N80: 25 | O80: 25 | P80: 25
D81: Other liabilities | E81: days | L81: 20 | M81: 20 | N81: 20 | O81: 20 | P81: 20
C83: Operational Expenses
D84: Human Resources (staff)
D85: Manager | E85: no. | L85: 1 | M85: 1 | N85: 1 | O85: 1 | P85: 1
D86: Sales personnel/Stock keeper | E86: no. | L86: 3 | M86: 3 | N86: 3 | O86: 3 | P86: 3
D87: Accountant | E87: no. | L87: 1 | M87: 1 | N87: 1 | O87: 1 | P87: 1
D88: Security | E88: no. | L88: 2 | M88: 2 | N88: 2 | O88: 2 | P88: 2
D89: Other staff | E89: no. | L89: 2 | M89: 2 | N89: 2 | O89: 2 | P89: 2
D91: Human Resources (Salary)
D92: =D85 -> Manager | E92: =Currency&"/month" -> $/month | L92: 5000 | M92: 5000 | N92: 5000 | O92: 5050 | P92: 5100
D93: =D86 -> Sales personnel/Stock keeper | E93: =Currency&"/month" -> $/month | L93: 1500 | M93: 1500 | N93: 1500 | O93: 1550 | P93: 1600
D94: =D87 -> Accountant | E94: =Currency&"/month" -> $/month | L94: 2000 | M94: 2000 | N94: 2000 | O94: 2050 | P94: 2100
D95: =D88 -> Security | E95: =Currency&"/month" -> $/month | L95: 1000 | M95: 1000 | N95: 1000 | O95: 1050 | P95: 1100
D96: =D89 -> Other staff | E96: =Currency&"/month" -> $/month | L96: 750 | M96: 750 | N96: 750 | O96: 800 | P96: 850
D98: Selling, General & Admin Expenses
D99: Rent | E99: =Currency&"/month" -> $/month | L99: 1250 | M99: 1250 | N99: 1250 | O99: 1300 | P99: 1300
D100: Utilities | E100: =Currency&"/month" -> $/month | L100: 300 | M100: 300 | N100: 300 | O100: 350 | P100: 350
D101: Maintenance | E101: =Currency&"/month" -> $/month | L101: 250 | M101: 250 | N101: 250 | O101: 300 | P101: 300
D102: Internet & Subscriptions | E102: =Currency&"/month" -> $/month | L102: 500 | M102: 500 | N102: 500 | O102: 550 | P102: 550
D103: Marketing | E103: =Currency&"/month" -> $/month | L103: 1000 | M103: 1000 | N103: 1000 | O103: 1050 | P103: 1050
D104: Insurance | E104: =Currency&"/month" -> $/month | L104: 420 | M104: 420 | N104: 420 | O104: 470 | P104: 470
D105: Miscellaneous | E105: =Currency&"/month" -> $/month | L105: 400 | M105: 400 | N105: 400 | O105: 450 | P105: 450
B107: Revenue & Cost
C108: Revenue
D109: Product
D110: Paint Size 1
D111: Paint Size 2
D112: Paint Size 3
D114: Product Price
D115: =D110 -> Paint Size 1 | E115: =Currency&"/unit" -> $/unit | F115: 159
D116: =D111 -> Paint Size 2 | E116: =Currency&"/unit" -> $/unit | F116: 79
D117: =D112 -> Paint Size 3 | E117: =Currency&"/unit" -> $/unit | F117: 49
D119: Product Quantity
D120: =D110 -> Paint Size 1 | E120: units/month | F120: 200
...

Sheet Scenarios
B2: =Guide!$F$33 -> TOWV Bootcamp Limited
B3: Scenarios & Sensitivity
G4: period start | L4: =K5+1 -> 44562 | M4: =L5+1 -> 44927 | N4: =M5+1 -> 45292 | O4: =N5+1 -> 45658 | P4: =O5+1 -> 46023
C5: =Scenario -> Live Scenario: Base Case | G5: Period end | K5: =Guide!F39-1 -> 44561 | L5: =EDATE(K5,Guide!$F$41) -> 44926 | M5: =EDATE(L5,Guide!$F$41) -> 45291 | N5: =EDATE(M5,Guide!$F$41) -> 45657 | O5: =EDATE(N5,Guide!$F$41) -> 46022 | P5: =EDATE(O5,Guide!$F$41) -> 46387
C6: Model balance check | G6: Years | L6: =YEAR(L4) -> 2022 | M6: =YEAR(M4) -> 2023 | N6: =YEAR(N4) -> 2024 | O6: =YEAR(O4) -> 2025 | P6: =YEAR(P4) -> 2026
D7: Descriptions | E7: unit | F7: Inputs/Linked | G7: Row Aver. | H7: Row Total
B10: Scenarios
D11: {="Live Scenario: "&INDEX(S_Case,S_Switch)} -> Live Scenario: Base Case
C12: 1 | D12: {=S_Case} -> Base Case | E12: 1
C13: 2 | D13: Conservative Case
C14: 3 | D14: Best Case
C15: 4 | D15: Worse Case
D18: Inflation Rate | L18: =CHOOSE(S_Switch,L19,L20,L21,L22) -> 0 | M18: =CHOOSE(S_Switch,M19,M20,M21,M22) -> 0.025 | N18: =CHOOSE(S_Switch,N19,N20,N21,N22) -> 0.0245 | O18: =CHOOSE(S_Switch,O19,O20,O21,O22) -> 0.0237 | P18: =CHOOSE(S_Switch,P19,P20,P21,P22) -> 0.0225
D19: {=S_Case} -> Base Case | L19: 0 | M19: 0.025 | N19: 0.0245 | O19: 0.0237 | P19: 0.0225
D20: Conservative Case | E20: -0.005 | L20: 0 | M20: =M19+$E20 -> 0.02 | N20: =N19+$E20 -> 0.0195 | O20: =O19+$E20 -> 0.0187 | P20: =P19+$E20 -> 0.0175
D21: Best Case | E21: -0.01 | L21: 0 | M21: =M19+$E21 -> 0.015 | N21: =N19+$E21 -> 0.0145 | O21: =O19+$E21 -> 0.0137 | P21: =P19+$E21 -> 0.0125
D22: Worse Case | E22: 0.005 | L22: 0 | M22: =M19+$E22 -> 0.03 | N22: =N19+$E22 -> 0.0295 | O22: =O19+$E22 -> 0.0287 | P22: =P19+$E22 -> 0.0275
D25: CAGR | L25: =CHOOSE(S_Switch,L26,L27,L28,L29) -> 0 | M25: =CHOOSE(S_Switch,M26,M27,M28,M29) -> 0.045 | N25: =CHOOSE(S_Switch,N26,N27,N28,N29) -> 0.055 | O25: =CHOOSE(S_Switch,O26,O27,O28,O29) -> 0.1005 | P25: =CHOOSE(S_Switch,P26,P27,P28,P29) -> 0.025
D26: {=S_Case} -> Base Case | L26: 0 | M26: 0.045 | N26: 0.055 | O26: 0.1005 | P26: 0.025
D27: Conservative Case | E27: 0.01 | L27: 0 | M27: =M26+$E27 -> 0.055 | N27: =N26+$E27 -> 0.065 | O27: =O26+$E27 -> 0.1105 | P27: =P26+$E27 -> 0.035
D28: Best Case | E28: 0.05 | L28: 0 | M28: =M26+$E28 -> 0.095 | N28: =N26+$E28 -> 0.105 | O28: =O26+$E28 -> 0.1505 | P28: =P26+$E28 -> 0.075
D29: Worse Case | E29: -0.025 | L29: 0 | M29: =M26+$E29 -> 0.02 | N29: =N26+$E29 -> 0.03 | O29: =O26+$E29 -> 0.0755 | P29: =P26+$E29 -> 0

Sheet Calc
B2: =Guide!$F$33 -> TOWV Bootcamp Limited
B3: Calculations & Schedule
G4: period start | L4: =K5+1 -> 44562 | M4: =L5+1 -> 44927 | N4: =M5+1 -> 45292 | O4: =N5+1 -> 45658 | P4: =O5+1 -> 46023
C5: =Scenario -> Live Scenario: Base Case | G5: Period end | K5: =Guide!F39-1 -> 44561 | L5: =EDATE(K5,Guide!$F$41) -> 44926 | M5: =EDATE(L5,Guide!$F$41) -> 45291 | N5: =EDATE(M5,Guide!$F$41) -> 45657 | O5: =EDATE(N5,Guide!$F$41) -> 46022 | P5: =EDATE(O5,Guide!$F$41) -> 46387
C6: Model balance check | G6: Years | L6: =YEAR(L4) -> 2022 | M6: =YEAR(M4) -> 2023 | N6: =YEAR(N4) -> 2024 | O6: =YEAR(O4) -> 2025 | P6: =YEAR(P4) -> 2026
D7: Descriptions | E7: unit | F7: Inputs/Linked | G7: Row Aver. | H7: Row Total
B9: Funding Calculations
C10: Loan Schedule
D11: Assumptions Linked
D12: =Inputs!D35 -> Long term loan | E12: =Inputs!E35 -> $ | H12: =SUM(L12:P12) -> 100000 | L12: =Inputs!L35 -> 100000 | M12: =Inputs!M35 -> 0 | N12: =Inputs!N35 -> 0 | O12: =Inputs!O35 -> 0 | P12: =Inputs!P35 -> 0
D13: =Inputs!D42 -> Loan period | E13: =Inputs!E42 -> years | F13: =Inputs!F42 -> 4
D14: =Inputs!D43 -> Loan interest rate | E14: =Inputs!E43 -> %age | L14: =Inputs!L43 -> 0.0716 | M14: =Inputs!M43 -> 0.0716 | N14: =Inputs!N43 -> 0.0716 | O14: =Inputs!O43 -> 0.0716 | P14: =Inputs!P43 -> 0.0716
D16: Loan for schedule | E16: =Currency -> $ | K16: =L12 -> 100000 | L16: =M12 -> 0 | M16: =N12 -> 0 | N16: =O12 -> 0 | O16: =P12 -> 0 | P16: =Q12
D17: Loan for cashflow | E17: =Currency -> $ | L17: =L12 -> 100000 | M17: =M12 -> 0 | N17: =N12 -> 0 | O17: =O12 -> 0 | P17: =P12 -> 0
D19: Loan Schedule
D20: Beginning balance | E20: =Currency -> $ | L20: =K23 -> 100000 | M20: =L23 -> 77530.48 | N20: =M23 -> 53452.142 | O20: =N23 -> 27649.795 | P20: =O23 -> 1.6370905e-10
D21: Add: New loan | E21: =Currency -> $ | L21: =L16 -> 0 | M21: =M16 -> 0 | N21: =N16 -> 0 | O21: =O16 -> 0 | P21: =P16
D22: Less: repayment | E22: =Currency -> $ | F22: =ABS(PMT(L14,F13,H12)) -> 29629.52 | L22: =($F$22-L25)*L28 -> 22469.52 | M22: =($F$22-M25)*M28 -> 24078.338 | N22: =($F$22-N25)*N28 -> 25802.347 | O22: =($F$22-O25)*O28 -> 27649.795 | P22: =($F$22-P25)*P28 -> 0
D23: Ending balance | E23: =Currency -> $ | K23: =K16 -> 100000 | L23: =L20+L21-L22 -> 77530.48 | M23: =M20+M21-M22 -> 53452.142 | N23: =N20+N21-N22 -> 27649.795 | O23: =O20+O21-O22 -> 1.6370905e-10 | P23: =P20+P21-P22 -> 1.6370905e-10
D25: Interest expense | E25: =Currency -> $ | L25: =L20*L14 -> 7160 | M25: =M20*M14 -> 5551.1824 | N25: =N20*N14 -> 3827.1734 | O25: =O20*O14 -> 1979.7253 | P25: =P20*P14 -> 0
L27: =K27+1 -> 1 | M27: =L27+1 -> 2 | N27: =M27+1 -> 3 | O27: =N27+1 -> 4 | P27: =O27+1 -> 5
D28: Mask & Flag | L28: =L27<=$F$13 -> TRUE | M28: =M27<=$F$13 -> TRUE | N28: =N27<=$F$13 -> TRUE | O28: =O27<=$F$13 -> TRUE | P28: =P27<=$F$13 -> FALSE
C30: Equity Schedule
D31: =Inputs!D37 -> Equity | E31: =Inputs!E37 -> $ | L31: =Inputs!L37 -> 150000 | M31: =Inputs!M37 -> 0 | N31: =Inputs!N37 -> 0 | O31: =Inputs!O37 -> 0 | P31: =Inputs!P37 -> 0
D32: =Inputs!D46 -> Dividend payout ratio | E32: =Inputs!E46 -> %age | L32: =Inputs!L46 -> 0.3 | M32: =Inputs!M46 -> 0.3 | N32: =Inputs!N46 -> 0.3 | O32: =Inputs!O46 -> 0.3 | P32: =Inputs!P46 -> 0.3
D34: Equity Schedule
D35: Beginning balance | E35: =Currency -> $ | L35: =K37 | M35: =L37 -> 150000 | N35: =M37 -> 150000 | O35: =N37 -> 150000 | P35: =O37 -> 150000
D36: Change | E36: =Currency -> $ | L36: =L31 -> 150000 | M36: =M31 -> 0 | N36: =N31 -> 0 | O36: =O31 -> 0 | P36: =P31 -> 0
D37: Ending balance | E37: =Currency -> $ | L37: =L35+L36 -> 150000 | M37: =M35+M36 -> 150000 | N37: =N35+N36 -> 150000 | O37: =O35+O36 -> 150000 | P37: =P35+P36 -> 150000
D39: Retained earnings
D40: Beginning balance | E40: =Currency -> $ | L40: =K43 | M40: =L43 -> 65257.71 | N40: =M43 -> 155803.29 | O40: =N43 -> 249932.67 | P40: =O43 -> 352598.15
D41: Add: net profit | E41: =Currency -> $ | L41: =PL!L26*Div -> 93225.3 | M41: =PL!M26*Div -> 129350.83 | N41: =PL!N26*Div -> 134470.53 | O41: =PL!O26*Div -> 146664.98 | P41: =PL!P26*Div -> 138011.54
D42: Less: Dividends | E42: =Currency -> $ | L42: =(L41>0)*(L32*L41) -> 27967.59 | M42: =(M41>0)*(M32*M41) -> 38805.25 | N42: =(N41>0)*(N32*N41) -> 40341.16 | O42: =(O41>0)*(O32*O41) -> 43999.495 | P42: =(P41>0)*(P32*P41) -> 41403.463
D43: Ending balance | E43: =Currency -> $ | L43: =L40+L41-L42 -> 65257.71 | M43: =M40+M41-M42 -> 155803.29 | N43: =N40+N41-N42 -> 249932.67 | O43: =O40+O41-O42 -> 352598.15 | P43: =P40+P41-P42 -> 449206.23
B46: Use of funds & Capex
C47: Summarized Use of Funds
D48: Pre-operational expenses | E48: =Currency -> $ | L48: =SUM(Inputs!L50,Inputs!L51,Inputs!L52,Inputs!L53,Inputs!L62,Inputs!L63) -> 48500 | M48: =SUM(Inputs!M50,Inputs!M51,Inputs!M52,Inputs!M53,Inputs!M62,Inputs!M63) -> 0 | N48: =SUM(Inputs!N50,Inputs!N51,Inputs!N52,Inputs!N53,Inputs!N62,Inputs!N63) -> 0 | O48: =SUM(Inputs!O50,Inputs!O51,Inputs!O52,Inputs!O53,Inputs!O62,Inputs!O63) -> 0 | P48: =SUM(Inputs!P50,Inputs!P51,Inputs!P52,Inputs!P53,Inputs!P62,Inputs!P63) -> 0
D49: Assets | E49: =Currency -> $ | L49: =SUM(Inputs!L55:L58) -> 53000 | M49: =SUM(Inputs!M55:M58) -> 0 | N49: =SUM(Inputs!N55:N58) -> 0 | O49: =SUM(Inputs!O55:O58) -> 0 | P49: =SUM(Inputs!P55:P58) -> 0
D50: Inventory | E50: =Currency -> $ | L50: =Inputs!L60 -> 75000 | M50: =Inputs!M60 -> 0 | N50: =Inputs!N60 -> 0 | O50: =Inputs!O60 -> 0 | P50: =Inputs!P60 -> 0
D51: Pre-paid Rent & insurance | E51: =Currency -> $ | L51: =Inputs!L65+Inputs!L66 -> 20000 | M51: =Inputs!M65+Inputs!M66 -> 0 | N51: =Inputs!N65+Inputs!N66 -> 0 | O51: =Inputs!O65+Inputs!O66 -> 0 | P51: =Inputs!P65+Inputs!P66 -> 0
D52: Working cash | E52: =Currency -> $ | L52: =Inputs!L67 -> 53500 | M52: =Inputs!M67 -> 0 | N52: =Inputs!N67 -> 0 | O52: =Inputs!O67 -> 0 | P52: =Inputs!P67 -> 0
D53: Total use of funds | E53: =Currency -> $ | L53: =SUM(L48:L52) -> 250000 | M53: =SUM(M48:M52) -> 0 | N53: =SUM(N48:N52) -> 0 | O53: =SUM(O48:O52) -> 0 | P53: =SUM(P48:P52) -> 0
C55: Capex & Depreciation
D56: Assumptions linked
D57: =Inputs!D30 -> Maintenable capex | E57: =Inputs!E30 -> factor of dep. | L57: =Inputs!L30 -> 1 | M57: =Inputs!M30 -> 1.025 | N57: =Inputs!N30 -> 1.0496002 | O57: =Inputs!O30 -> 1.0727984 | P57: =Inputs!P30 -> 1.0930833
D58: Asset lifespan | E58: year | L58: =Inputs!$F$58 -> 5 | M58: =Inputs!$F$58 -> 5 | N58: =Inputs!$F$58 -> 5 | O58: =Inputs!$F$58 -> 5 | P58: =Inputs!$F$58 -> 5
D60: Asset Schedule
D61: Beginning balance | E61: =Currency -> $ | L61: =K64 | M61: =L64 -> 47700 | N61: =M64 -> 42532.5 | O61: =N64 -> 43058.263 | P61: =O64 -> 43829.925
D62: Add: New capex | E62: =Currency -> $ | L62: =L49+(K63*L57) -> 53000 | M62: =M49+(L63*M57) -> 5432.5 | N62: =N49+(M63*N57) -> 11125.763 | O62: =O49+(N63*O57) -> 11371.663 | P62: =P49+(O63*P57) -> 11586.683
D63: Less:Depreciation | E63: =Currency -> $ | L63: =L73 -> 5300 | M63: =M73 -> 10600 | N63: =N73 -> 10600 | O63: =O73 -> 10600 | P63: =P73 -> 10600
D64: Ending balance | E64: =Currency -> $ | L64: =L61+L62-L63 -> 47700 | M64: =M61+M62-M63 -> 42532.5 | N64: =N61+N62-N63 -> 43058.263 | O64: =O61+O62-O63 -> 43829.925 | P64: =P61+P62-P63 -> 44816.609
J67: Period | K67: Amount | L67: =L6 -> 2022 | M67: =M6 -> 2023 | N67: =N6 -> 2024 | O67: =O6 -> 2025 | P67: =P6 -> 2026
J68: {=TRANSPOSE(L6:P6)} -> 2022 | K68: {=TRANSPOSE(L62:P62)} -> 53000 | L68: =($K68/L$58)/2 -> 5300 | M68: =$K68/M$58 -> 10600 | N68: =$K68/N$58 -> 10600 | O68: =$K68/O$58 -> 10600 | P68: =$K68/P$58 -> 10600
J69: 2023 | M69: =($K69/M$58)/2 -> 0 | N69: =$K69/N$58 -> 0 | O69: =$K69/O$58 -> 0 | P69: =$K69/P$58 -> 0
J70: 2024 | N70: =($K70/N$58)/2 -> 0 | O70: =$K70/O$58 -> 0 | P70: =$K70/P$58 -> 0
J71: 2025 | O71: =($K71/O$58)/2 -> 0 | P71: =$K71/P$58 -> 0
J72: 2026 | P72: =($K72/P$58)/2 -> 0
K73: Total dep. | L73: =SUM(L68:L72) -> 5300 | M73: =SUM(M68:M72) -> 10600 | N73: =SUM(N68:N72) -> 10600 | O73: =SUM(O68:O72) -> 10600 | P73: =SUM(P68:P72) -> 10600
B76: Revenue & Cost Calculations
C77: Revenue
D78: Assumption Linked
D79: =Inputs!D13 -> Month in a period | E79: =Inputs!E13 -> month | L79: =Inputs!L13 -> 12 | M79: =Inputs!M13 -> 12 | N79: =Inputs!N13 -> 12 | O79: =Inputs!O13 -> 12 | P79: =Inputs!P13 -> 12
D80: =Inputs!D17 -> Inflation rate | E80: =Inputs!E17 -> %age | L80: =Inputs!L17 -> 0 | M80: =Inputs!M17 -> 0.025 | N80: =Inputs!N17 -> 0.0245 | O80: =Inputs!O17 -> 0.0237 | P80: =Inputs!P17 -> 0.0225
D81: =Inputs!D21 -> Product pricing growth | E81: =Inputs!E21 -> %age | L81: =Inputs!L21 -> 0 | M81: =Inputs!M21 -> 0 | N81: =Inputs!N21 -> 0 | O81: =Inputs!O21 -> 0 | P81: =Inputs!P21 -> 0
D82: =Inputs!D24 -> Volume growth rate (CAGR) | E82: =Inputs!E24 -> %age | L82: =Inputs!L24 -> 0 | M82: =Inputs!M24 -> 0.045 | N82: =Inputs!N24 -> 0.055 | O82: =Inputs!O24 -> 0.1005 | P82: =Inputs!P24 -> 0.025
D83: =Inputs!D130 -> Other cost | E83: =Inputs!E130 -> %age of sales | L83: =Inputs!$F$130 -> 0.025 | M83: =Inputs!$F$130 -> 0.025 | N83: =Inputs!$F$130 -> 0.025 | O83: =Inputs!$F$130 -> 0.025 | P83: =Inputs!$F$130 -> 0.025
D85: =Inputs!D114 -> Product Price
D86: =Inputs!D115 -> Paint Size 1 | E86: =Inputs!E115 -> $/unit | K86: =Inputs!F115 -> 159 | L86: =K86*(1+L$81) -> 159 | M86: =L86*(1+M$81) -> 159 | N86: =M86*(1+N$81) -> 159 | O86: =N86*(1+O$81) -> 159 | P86: =O86*(1+P$81) -> 159
D87: =Inputs!D116 -> Paint Size 2 | E87: =Inputs!E116 -> $/unit | K87: =Inputs!F116 -> 79 | L87: =K87*(1+L$81) -> 79 | M87: =L87*(1+M$81) -> 79 | N87: =M87*(1+N$81) -> 79 | O87: =N87*(1+O$81) -> 79 | P87: =O87*(1+P$81) -> 79
D88: =Inputs!D117 -> Paint Size 3 | E88: =Inputs!E117 -> $/unit | K88: =Inputs!F117 -> 49 | L88: =K88*(1+L$81) -> 49 | M88: =L88*(1+M$81) -> 49 | N88: =M88*(1+N$81) -> 49 | O88: =N88*(1+O$81) -> 49 | P88: =O88*(1+P$81) -> 49
D90: =Inputs!D119 -> Product Quantity
D91: =Inputs!D120 -> Paint Size 1 | E91: =Inputs!E120 -> units/month | K91: =Inputs!F120 -> 200 | L91: =K91*(1+L$82) -> 200 | M91: =L91*(1+M$82) -> 209 | N91: =M91*(1+N$82) -> 220.495 | O91: =N91*(1+O$82) -> 242.65475 | P91: =O91*(1+P$82) -> 248.72112
D92: =Inputs!D121 -> Paint Size 2 | E92: =Inputs!E121 -> units/month | K92: =Inputs!F121 -> 300 | L92: =K92*(1+L$82) -> 300 | M92: =L92*(1+M$82) -> 313.5 | N92: =M92*(1+N$82) -> 330.7425 | O92: =N92*(1+O$82) -> 363.98212 | P92: =O92*(1+P$82) -> 373.08167
D93: =Inputs!D122 -> Paint Size 3 | E93: =Inputs!E122 -> units/month | K93: =Inputs!F122 -> 400 | L93: =K93*(1+L$82) -> 400 | M93: =L93*(1+M$82) -> 418 | N93: =M93*(1+N$82) -> 440.99 | O93: =N93*(1+O$82) -> 485.3095 | P93: =O93*(1+P$82) -> 497.44223
D95: =D90 -> Product Quantity
D96: =D91 -> Paint Size 1 | E96: units/year | L96: =L91*L$79 -> 2400 | M96: =M91*M$79 -> 2508 | N96: =N91*N$79 -> 2645.94 | O96: =O91*O$79 -> 2911.857 | P96: =P91*P$79 -> 2984.6534
D97: =D92 -> Paint Size 2 | E97: units/year | L97: =L92*L$79 -> 3600 | M97: =M92*M$79 -> 3762 | N97: =N92*N$79 -> 3968.91 | O97: =O92*O$79 -> 4367.7855 | P97: =P92*P$79 -> 4476.9801
D98: =D93 -> Paint Size 3 | E98: units/year | L98: =L93*L$79 -> 4800 | M98: =M93*M$79 -> 5016 | N98: =N93*N$79 -> 5291.88 | O98: =O93*O$79 -> 5823.7139 | P98: =P93*P$79 -> 5969.3068
D99: Total Quantity | E99: units/year | L99: =SUM(L96:L98) -> 10800 | M99: =SUM(M96:M98) -> 11286 | N99: =SUM(N96:N98) -> 11906.73 | O99: =SUM(O96:O98) -> 13103.356 | P99: =SUM(P96:P98) -> 13430.94
D101: Revenue
D102: =D96 -> Paint Size 1 | E102: =Currency&"/year" -> $/year | L102: =L86*L96 -> 381600 | M102: =M86*M96 -> 398772 | N102: =N86*N96 -> 420704.46 | O102: =O86*O96 -> 462985.26 | P102: =P86*P96 -> 474559.89
D103: =D97 -> Paint Size 2 | E103: =Currency&"/year" -> $/year | L103: =L87*L97 -> 284400 | M103: =M87*M97 -> 297198 | N103: =N87*N97 -> 313543.89 | O103: =O87*O97 -> 345055.05 | P103: =P87*P97 -> 353681.43
D104: =D98 -> Paint Size 3 | E104: =Currency&"/year" -> $/year | L104: =L88*L98 -> 235200 | M104: =M88*M98 -> 245784 | N104: =N88*N98 -> 259302.12 | O104: =O88*O98 -> 285361.98 | P104: =P88*P98 -> 292496.03
D105: Total revenue | E105: =Currency&"/year" -> $/year | L105: =SUM(L102:L104) -> 901200 | M105: =SUM(M102:M104) -> 941754 | N105: =SUM(N102:N104) -> 993550.47 | O105: =SUM(O102:O104) -> 1093402.3 | P105: =SUM(P102:P104) -> 1120737.4
C107: Cost
D108: =Inputs!D125 -> Cost of Product
D109: =Inputs!D126 -> Paint Size 1 | E109: =Inputs!E126 -> $/unit | K109: =Inputs!F126 -> 89.6 | L109: =K109*(1+L$80) -> 89.6 | M109: =L109*(1+M$80) -> 91.84 | N109: =M109*(1+N$80) -> 94.09008 | O109: =N109*(1+O$80) -> 96.320015 | P109: =O109*(1+P$80) -> 98.487215
D110: =Inputs!D127 -> Paint Size 2 | E110: =Inputs!E127 -> $/unit | K110: =Inputs!F127 -> 41.7 | L110: =K110*(1+L$80) -> 41.7 | M110: =L110*(1+M$80) -> 42.7425 | N110: =M110*(1+N$80) -> 43.789691 | O110: =N110*(1+O$80) -> 44.827507 | P110: =O110*(1+P$80) -> 45.836126
D111: =Inputs!D128 -> Paint Size 3 | E111: =Inputs!E128 -> $/unit | K111: =Inputs!F128 -> 21.5 | L111: =K111*(1+L$80) -> 21.5 | M111: =L111*(1+M$80) -> 22.0375 | N111: =M111*(1+N$80) -> 22.577419 | O111: =N111*(1+O$80) -> 23.112504 | P111: =O111*(1+P$80) -> 23.632535
D113: =D95 -> Product Quantity
D114: =D96 -> Paint Size 1 | E114: =E96 -> units/year | L114: =L96 -> 2400 | M114: =M96 -> 2508 | N114: =N96 -> 2645.94 | O114: =O96 -> 2911.857 | P114: =P96 -> 2984.6534
D115: =D97 -> Paint Size 2 | E115: =E97 -> units/year | L115: =L97 -> 3600 | M115: =M97 -> 3762 | N115: =N97 -> 3968.91 | O115: =O97 -> 4367.7855 | P115: =P97 -> 4476.9801
D116: =D98 -> Paint Size 3 | E116: =E98 -> units/year | L116: =L98 -> 4800 | M116: =M98 -> 5016 | N116: =N98 -> 5291.88 | O116: =O98 -> 5823.7139 | P116: =P98 -> 5969.3068
D118: Total cost of product
D119: =D109 -> Paint Size 1 | E119: =Currency&"/year" -> $/year | L119: =L109*L114 -> 215040 | M119: =M109*M114 -> 230334.72 | N119: =N109*N114 -> 248956.71 | O119: =O109*O114 -> 280470.11 | P119: =P109*P114 -> 293950.2
D120: =D110 -> Paint Size 2 | E120: =Currency&"/year" -> $/year | L120: =L110*L115 -> 150120 | M120: =M110*M115 -> 160797.29 | N120: =N110*N115 -> 173797.34 | O120: =O110*O115 -> 195796.93 | P120: =P110*P115 -> 205207.42
D121: =D111 -> Paint Size 3 | E121: =Currency&"/year" -> $/year | L121: =L111*L116 -> 103200 | M121: =M111*M116 -> 110540.1 | N121: =N111*N116 -> 119476.99 | O121: =O111*O116 -> 134600.61 | P121: =P111*P116 -> 141069.85
D122: Other direct cost | E122: =Currency&"/year" -> $/year | L122: =L105*L83 -> 22530 | M122: =M105*M83 -> 23543.85 | N122: =N105*N83 -> 24838.762 | O122: =O105*O83 -> 27335.057 | P122: =P105*P83 -> 28018.434
D123: Total cost of sales | E123: =Currency&"/year" -> $/year | L123: =SUM(L119:L122) -> 490890 | M123: =SUM(M119:M122) -> 525215.95 | N123: =SUM(N119:N122) -> 567069.8 | O123: =SUM(O119:O122) -> 638202.71 | P123: =SUM(P119:P122) -> 668245.91
B127: Operational Expenses
...

Sheet PL
B2: =Guide!$F$33 -> TOWV Bootcamp Limited
B3: Profit or Loss Account
G4: period start | L4: =K5+1 -> 44562 | M4: =L5+1 -> 44927 | N4: =M5+1 -> 45292 | O4: =N5+1 -> 45658 | P4: =O5+1 -> 46023
C5: =Scenario -> Live Scenario: Base Case | G5: Period end | K5: =Guide!F39-1 -> 44561 | L5: =EDATE(K5,Guide!$F$41) -> 44926 | M5: =EDATE(L5,Guide!$F$41) -> 45291 | N5: =EDATE(M5,Guide!$F$41) -> 45657 | O5: =EDATE(N5,Guide!$F$41) -> 46022 | P5: =EDATE(O5,Guide!$F$41) -> 46387
C6: Model balance check | G6: Years | L6: =YEAR(L4) -> 2022 | M6: =YEAR(M4) -> 2023 | N6: =YEAR(N4) -> 2024 | O6: =YEAR(O4) -> 2025 | P6: =YEAR(P4) -> 2026
D7: Descriptions | E7: unit | F7: Inputs/Linked | G7: Row Aver. | H7: Trend
C9: Summarized Profit or Loss Account
D10: Revenue | E10: =Currency&"'000" -> $'000 | G10: =AVERAGE(L10:P10) -> 1010.1288 | L10: =Calc!L105/Div -> 901.2 | M10: =Calc!M105/Div -> 941.754 | N10: =Calc!N105/Div -> 993.55047 | O10: =Calc!O105/Div -> 1093.4023 | P10: =Calc!P105/Div -> 1120.7374
D11: yoy growth | E11: %age | G11: =AVERAGE(L11:P11) -> 0.0451 | L11: =IFERROR(L10/K10-1,0) -> 0 | M11: =IFERROR(M10/L10-1,0) -> 0.045 | N11: =IFERROR(N10/M10-1,0) -> 0.055 | O11: =IFERROR(O10/N10-1,0) -> 0.1005 | P11: =IFERROR(P10/O10-1,0) -> 0.025
D12: Cost of Sales | E12: =Currency&"'000" -> $'000 | G12: =AVERAGE(L12:P12) -> 577.92487 | L12: =Calc!L123/Div -> 490.89 | M12: =Calc!M123/Div -> 525.21596 | N12: =Calc!N123/Div -> 567.0698 | O12: =Calc!O123/Div -> 638.20271 | P12: =Calc!P123/Div -> 668.24591
D13: COS growth | E13: %age | G13: =AVERAGE(L13:P13) -> 0.064425783 | L13: =IFERROR(L12/K12-1,0) -> 0 | M13: =IFERROR(M12/L12-1,0) -> 0.069925961 | N13: =IFERROR(N12/M12-1,0) -> 0.079688834 | O13: =IFERROR(O12/N12-1,0) -> 0.12543941 | P13: =IFERROR(P12/O12-1,0) -> 0.047074703
D14: Gross Profit | E14: =Currency&"'000" -> $'000 | G14: =AVERAGE(L14:P14) -> 432.20395 | L14: =L10-L12 -> 410.31 | M14: =M10-M12 -> 416.53805 | N14: =N10-N12 -> 426.48067 | O14: =O10-O12 -> 455.19959 | P14: =P10-P12 -> 452.49144
D15: gross profit margin | E15: %age | G15: =AVERAGE(L15:P15) -> 0.42938031 | L15: =L14/L10 -> 0.45529294 | M15: =M14/M10 -> 0.44230027 | N15: =N14/N10 -> 0.42924912 | O15: =O14/O10 -> 0.41631483 | P15: =P14/P10 -> 0.40374441
D16: SG&A | E16: =Currency&"'000" -> $'000 | G16: =AVERAGE(L16:P16) -> 255.51426 | L16: =Calc!L186/Div -> 277.94 | M16: =Calc!M186/Div -> 235.176 | N16: =Calc!N186/Div -> 240.82028 | O16: =Calc!O186/Div -> 256.44173 | P16: =Calc!P186/Div -> 267.19329
D17: opex to revenue | E17: %age | G17: =AVERAGE(L17:P17) -> 0.25469197 | L17: =L16/L10 -> 0.30841101 | M17: =M16/M10 -> 0.24972126 | N17: =N16/N10 -> 0.24238354 | O17: =O16/O10 -> 0.23453557 | P17: =P16/P10 -> 0.23840848
D18: EBITDA | E18: =Currency&"'000" -> $'000 | G18: =AVERAGE(L18:P18) -> 176.68969 | L18: =L14-L16 -> 132.37 | M18: =M14-M16 -> 181.36204 | N18: =N14-N16 -> 185.66039 | O18: =O14-O16 -> 198.75786 | P18: =P14-P16 -> 185.29815
D19: ebitda margin | E19: %age | G19: =AVERAGE(L19:P19) -> 0.17468834 | L19: =L18/L10 -> 0.14688194 | M19: =M18/M10 -> 0.192579 | N19: =N18/N10 -> 0.18686558 | O19: =O18/O10 -> 0.18177926 | P19: =P18/P10 -> 0.16533593
D20: Depreciation & Amort. | E20: =Currency&"'000" -> $'000 | G20: =AVERAGE(L20:P20) -> 9.54 | L20: =Calc!L63/Div -> 5.3 | M20: =Calc!M63/Div -> 10.6 | N20: =Calc!N63/Div -> 10.6 | O20: =Calc!O63/Div -> 10.6 | P20: =Calc!P63/Div -> 10.6
D21: dep. to sales | E21: multiple | G21: =AVERAGE(L21:P21) -> 0.0093916038 | L21: =L20/L10 -> 0.0058810475 | M21: =M20/M10 -> 0.011255593 | N21: =N20/N10 -> 0.010668809 | O21: =O20/O10 -> 0.0096945105 | P21: =P20/P10 -> 0.009458059
D22: EBIT | E22: =Currency&"'000" -> $'000 | G22: =AVERAGE(L22:P22) -> 167.14969 | H22: =IFERROR(__xludf.DUMMYFUNCTION("ARRAY_CONSTRAIN(ARRAYFORMULA(SPARKLINE(PL!L22:P22, {""charttype"",""line"";""color"",""#376092"";""empty"",""ignore"";""nan"",""convert""})), 1, 1)"),"") | L22: =L18-L20 -> 127.07 | M22: =M18-M20 -> 170.76205 | N22: =N18-N20 -> 175.06039 | O22: =O18-O20 -> 188.15786 | P22: =P18-P20 -> 174.69815
D23: Interest expense | E23: =Currency&"'000" -> $'000 | G23: =AVERAGE(L23:P23) -> 3.7036162 | L23: =Calc!L25/Div -> 7.16 | M23: =Calc!M25/Div -> 5.5511824 | N23: =Calc!N25/Div -> 3.8271734 | O23: =Calc!O25/Div -> 1.9797253 | P23: =Calc!P25/Div -> 0
D24: EBT | E24: =Currency&"'000" -> $'000 | G24: =AVERAGE(L24:P24) -> 163.44607 | H24: =IFERROR(__xludf.DUMMYFUNCTION("ARRAY_CONSTRAIN(ARRAYFORMULA(SPARKLINE(PL!L24:P24, {""charttype"",""line"";""color"",""#376092"";""empty"",""ignore"";""nan"",""convert""})), 1, 1)"),"") | L24: =L22-L23 -> 119.91 | M24: =M22-M23 -> 165.21086 | N24: =N22-N23 -> 171.23321 | O24: =O22-O23 -> 186.17814 | P24: =P22-P23 -> 174.69815
D25: Provision for tax | E25: =Currency&"'000" -> $'000 | G25: =AVERAGE(L25:P25) -> 35.101435 | L25: =Calc!L191/Div -> 26.6847 | M25: =Calc!M191/Div -> 35.860029 | N25: =Calc!N191/Div -> 36.762681 | O25: =Calc!O191/Div -> 39.513151 | P25: =Calc!P191/Div -> 36.686612
D26: Net profit | E26: =Currency&"'000" -> $'000 | G26: =AVERAGE(L26:P26) -> 128.34464 | H26: =IFERROR(__xludf.DUMMYFUNCTION("ARRAY_CONSTRAIN(ARRAYFORMULA(SPARKLINE(PL!L26:P26, {""charttype"",""line"";""color"",""#376092"";""empty"",""ignore"";""nan"",""convert""})), 1, 1)"),"") | L26: =L24-L25 -> 93.2253 | M26: =M24-M25 -> 129.35083 | N26: =N24-N25 -> 134.47053 | O26: =O24-O25 -> 146.66498 | P26: =P24-P25 -> 138.01154
D27: net profit margin | E27: %age | G27: =AVERAGE(L27:P27) -> 0.126684 | L27: =L26/L10 -> 0.10344574 | M27: =M26/M10 -> 0.13735098 | N27: =N26/N10 -> 0.13534343 | O27: =O26/O10 -> 0.13413634 | P27: =P26/P10 -> 0.12314352

Sheet BS
B2: =Guide!$F$33 -> TOWV Bootcamp Limited
B3: Balance Sheet
G4: period start | L4: =K5+1 -> 44562 | M4: =L5+1 -> 44927 | N4: =M5+1 -> 45292 | O4: =N5+1 -> 45658 | P4: =O5+1 -> 46023
C5: =Scenario -> Live Scenario: Base Case | G5: Period end | K5: =Guide!F39-1 -> 44561 | L5: =EDATE(K5,Guide!$F$41) -> 44926 | M5: =EDATE(L5,Guide!$F$41) -> 45291 | N5: =EDATE(M5,Guide!$F$41) -> 45657 | O5: =EDATE(N5,Guide!$F$41) -> 46022 | P5: =EDATE(O5,Guide!$F$41) -> 46387
C6: Model balance check | G6: Years | L6: =YEAR(L4) -> 2022 | M6: =YEAR(M4) -> 2023 | N6: =YEAR(N4) -> 2024 | O6: =YEAR(O4) -> 2025 | P6: =YEAR(P4) -> 2026
D7: Descriptions | E7: unit | F7: Inputs/Linked | G7: Row Aver. | H7: Row Total | K7: balanc check | L7: =IF(L20=L37,"OK",L20-L37) -> OK | M7: =IF(M20=M37,"OK",M20-M37) -> OK | N7: =IF(N20=N37,"OK",N20-N37) -> OK | O7: =IF(O20=O37,"OK",O20-O37) -> OK | P7: =IF(P20=P37,"OK",P20-P37) -> OK
B9: Balance Sheet
C10: Assets
D11: Non current Assets (NCA)
D12: Net PPE | E12: =Currency&"'000" -> $'000 | G12: =AVERAGE(L12:P12) -> 44.387459 | L12: =Calc!L64/Div -> 47.7 | M12: =Calc!M64/Div -> 42.5325 | N12: =Calc!N64/Div -> 43.058263 | O12: =Calc!O64/Div -> 43.829926 | P12: =Calc!P64/Div -> 44.816609
D13: Total NCA | E13: =Currency&"'000" -> $'000 | G13: =AVERAGE(L13:P13) -> 44.387459 | L13: =SUM(L12) -> 47.7 | M13: =SUM(M12) -> 42.5325 | N13: =SUM(N12) -> 43.058263 | O13: =SUM(O12) -> 43.829926 | P13: =SUM(P12) -> 44.816609
D14: Current Assets (CA)
D15: Inventories | E15: =Currency&"'000" -> $'000 | G15: =AVERAGE(L15:P15) -> 63.300274 | L15: =Calc!L214/Div -> 53.796164 | M15: =Calc!M214/Div -> 57.557913 | N15: =Calc!N214/Div -> 61.974842 | O15: =Calc!O214/Div -> 69.940023 | P15: =Calc!P214/Div -> 73.232428
D16: Trade receivables | E16: =Currency&"'000" -> $'000 | G16: =AVERAGE(L16:P16) -> 69.149719 | L16: =Calc!L215/Div -> 61.726027 | M16: =Calc!M215/Div -> 64.503699 | N16: =Calc!N215/Div -> 67.865469 | O16: =Calc!O215/Div -> 74.890568 | P16: =Calc!P215/Div -> 76.762832
D17: Prepayment | E17: =Currency&"'000" -> $'000 | G17: =AVERAGE(L17:P17) -> 20.990356 | L17: =Calc!L216/Div -> 22.844384 | M17: =Calc!M216/Div -> 19.329534 | N17: =Calc!N216/Div -> 19.739367 | O17: =Calc!O216/Div -> 21.077402 | P17: =Calc!P216/Div -> 21.961092
D18: Cash & Cash equivalent | E18: =Currency&"'000" -> $'000 | G18: =AVERAGE(L18:P18) -> 352.52046 | L18: =CF!L36 -> 208.02001 | M18: =CF!M36 -> 283.35455 | N18: =CF!N36 -> 347.79738 | O18: =CF!O36 -> 416.44451 | P18: =CF!P36 -> 506.98584
D19: Total CA | E19: =Currency&"'000" -> $'000 | G19: =AVERAGE(L19:P19) -> 505.96081 | L19: =SUM(L15:L18) -> 346.38659 | M19: =SUM(M15:M18) -> 424.7457 | N19: =SUM(N15:N18) -> 497.37706 | O19: =SUM(O15:O18) -> 582.3525 | P19: =SUM(P15:P18) -> 678.9422
D20: Total Assets | E20: =Currency&"'000" -> $'000 | G20: =AVERAGE(L20:P20) -> 550.34827 | L20: =L13+L19 -> 394.08659 | M20: =M13+M19 -> 467.2782 | N20: =N13+N19 -> 540.43532 | O20: =O13+O19 -> 626.18243 | P20: =P13+P19 -> 723.75881
C21: Liabilities
D22: Non current Lialbilities (NCL)
D23: Long term loan | E23: =Currency&"'000" -> $'000 | G23: =AVERAGE(L23:P23) -> 31.726483 | L23: =Calc!L23/Div -> 77.53048 | M23: =Calc!M23/Div -> 53.452142 | N23: =Calc!N23/Div -> 27.649795 | O23: =Calc!O23/Div -> 0 | P23: =Calc!P23/Div -> 0
D24: Total NCL | E24: =Currency&"'000" -> $'000 | G24: =AVERAGE(L24:P24) -> 31.726483 | L24: =SUM(L23) -> 77.53048 | M24: =SUM(M23) -> 53.452142 | N24: =SUM(N23) -> 27.649795 | O24: =SUM(O23) -> 0 | P24: =SUM(P23) -> 0
D25: Current Liabilities (CL)
D26: Trade payables | E26: =Currency&"'000" -> $'000 | G26: =AVERAGE(L26:P26) -> 47.475206 | L26: =Calc!L219/Div -> 40.347123 | M26: =Calc!M219/Div -> 43.168435 | N26: =Calc!N219/Div -> 46.481131 | O26: =Calc!O219/Div -> 52.455017 | P26: =Calc!P219/Div -> 54.924321
D27: Accrued expenses | E27: =Currency&"'000" -> $'000 | G27: =AVERAGE(L27:P27) -> 17.491963 | L27: =Calc!L220/Div -> 19.036986 | M27: =Calc!M220/Div -> 16.107945 | N27: =Calc!N220/Div -> 16.449473 | O27: =Calc!O220/Div -> 17.564502 | P27: =Calc!P220/Div -> 18.30091
D28: Other liabilities | E28: =Currency&"'000" -> $'000 | G28: =AVERAGE(L28:P28) -> 13.993571 | L28: =Calc!L221/Div -> 15.229589 | M28: =Calc!M221/Div -> 12.886356 | N28: =Calc!N221/Div -> 13.159578 | O28: =Calc!O221/Div -> 14.051601 | P28: =Calc!P221/Div -> 14.640728
D29: Tax payables | E29: =Currency&"'000" -> $'000 | G29: =AVERAGE(L29:P29) -> 35.101435 | L29: =PL!L25 -> 26.6847 | M29: =PL!M25 -> 35.860029 | N29: =PL!N25 -> 36.762681 | O29: =PL!O25 -> 39.513151 | P29: =PL!P25 -> 36.686612
D30: Total CL | E30: =Currency&"'000" -> $'000 | G30: =AVERAGE(L30:P30) -> 114.06217 | L30: =SUM(L26:L29) -> 101.2984 | M30: =SUM(M26:M29) -> 108.02277 | N30: =SUM(N26:N29) -> 112.85286 | O30: =SUM(O26:O29) -> 123.58427 | P30: =SUM(P26:P29) -> 124.55257
D31: Total Liabilities | E31: =Currency&"'000" -> $'000 | G31: =AVERAGE(L31:P31) -> 145.78866 | L31: =L24+L30 -> 178.82888 | M31: =M24+M30 -> 161.47491 | N31: =N24+N30 -> 140.50266 | O31: =O24+O30 -> 123.58427 | P31: =P24+P30 -> 124.55257
C32: Equity
D33: Equity
D34: Share capital | E34: =Currency&"'000" -> $'000 | G34: =AVERAGE(L34:P34) -> 150 | L34: =Calc!L37/Div -> 150 | M34: =Calc!M37/Div -> 150 | N34: =Calc!N37/Div -> 150 | O34: =Calc!O37/Div -> 150 | P34: =Calc!P37/Div -> 150
D35: Retained earnings | E35: =Currency&"'000" -> $'000 | G35: =AVERAGE(L35:P35) -> 254.55961 | L35: =Calc!L43/Div -> 65.25771 | M35: =Calc!M43/Div -> 155.80329 | N35: =Calc!N43/Div -> 249.93267 | O35: =Calc!O43/Div -> 352.59815 | P35: =Calc!P43/Div -> 449.20623
D36: Total Equity | E36: =Currency&"'000" -> $'000 | G36: =AVERAGE(L36:P36) -> 404.55961 | L36: =SUM(L34:L35) -> 215.25771 | M36: =SUM(M34:M35) -> 305.80329 | N36: =SUM(N34:N35) -> 399.93267 | O36: =SUM(O34:O35) -> 502.59815 | P36: =SUM(P34:P35) -> 599.20623
D37: Total Equity & Liabilities | E37: =Currency&"'000" -> $'000 | G37: =AVERAGE(L37:P37) -> 550.34827 | L37: =L36+L31 -> 394.08659 | M37: =M36+M31 -> 467.2782 | N37: =N36+N31 -> 540.43532 | O37: =O36+O31 -> 626.18243 | P37: =P36+P31 -> 723.75881

Sheet CF
B2: =Guide!$F$33 -> TOWV Bootcamp Limited
B3: Cashflow Statement
G4: period start | L4: =K5+1 -> 44562 | M4: =L5+1 -> 44927 | N4: =M5+1 -> 45292 | O4: =N5+1 -> 45658 | P4: =O5+1 -> 46023
C5: =Scenario -> Live Scenario: Base Case | G5: Period end | K5: =Guide!F39-1 -> 44561 | L5: =EDATE(K5,Guide!$F$41) -> 44926 | M5: =EDATE(L5,Guide!$F$41) -> 45291 | N5: =EDATE(M5,Guide!$F$41) -> 45657 | O5: =EDATE(N5,Guide!$F$41) -> 46022 | P5: =EDATE(O5,Guide!$F$41) -> 46387
C6: Model balance check | G6: Years | L6: =YEAR(L4) -> 2022 | M6: =YEAR(M4) -> 2023 | N6: =YEAR(N4) -> 2024 | O6: =YEAR(O4) -> 2025 | P6: =YEAR(P4) -> 2026
D7: Descriptions | E7: unit | F7: Inputs/Linked | G7: Row Aver. | H7: Row Total
C10: Cash flow from Operating Activities (CFFO)
D11: Profit before tax | E11: =Currency&"'000" -> $'000 | G11: =AVERAGE(L11:P11) -> 163.44607 | L11: =PL!L24 -> 119.91 | M11: =PL!M24 -> 165.21086 | N11: =PL!N24 -> 171.23321 | O11: =PL!O24 -> 186.17814 | P11: =PL!P24 -> 174.69815
D12: adjustment for non-cash
D13: Depreciation & amort. | E13: =Currency&"'000" -> $'000 | G13: =AVERAGE(L13:P13) -> 9.54 | L13: =PL!L20 -> 5.3 | M13: =PL!M20 -> 10.6 | N13: =PL!N20 -> 10.6 | O13: =PL!O20 -> 10.6 | P13: =PL!P20 -> 10.6
D14: Changes in OWC
D15: =BS!D15 -> Inventories | E15: =Currency&"'000" -> $'000 | G15: =AVERAGE(L15:P15) -> -14.646486 | L15: =BS!K15-BS!L15 -> -53.796164 | M15: =BS!L15-BS!M15 -> -3.7617485 | N15: =BS!M15-BS!N15 -> -4.4169289 | O15: =BS!N15-BS!O15 -> -7.9651808 | P15: =BS!O15-BS!P15 -> -3.2924058
D16: =BS!D16 -> Trade receivables | E16: =Currency&"'000" -> $'000 | G16: =AVERAGE(L16:P16) -> -15.352566 | L16: =BS!K16-BS!L16 -> -61.726027 | M16: =BS!L16-BS!M16 -> -2.7776712 | N16: =BS!M16-BS!N16 -> -3.3617706 | O16: =BS!N16-BS!O16 -> -7.0250987 | P16: =BS!O16-BS!P16 -> -1.8722642
D17: =BS!D17 -> Prepayment | E17: =Currency&"'000" -> $'000 | G17: =AVERAGE(L17:P17) -> -4.3922184 | L17: =BS!K17-BS!L17 -> -22.844384 | M17: =BS!L17-BS!M17 -> 3.5148493 | N17: =BS!M17-BS!N17 -> -0.40983308 | O17: =BS!N17-BS!O17 -> -1.3380348 | P17: =BS!O17-BS!P17 -> -0.88368996
D18: =BS!D26 -> Trade payables | E18: =Currency&"'000" -> $'000 | G18: =AVERAGE(L18:P18) -> 10.984864 | L18: =BS!L26-BS!K26 -> 40.347123 | M18: =BS!M26-BS!L26 -> 2.8213114 | N18: =BS!N26-BS!M26 -> 3.3126967 | O18: =BS!O26-BS!N26 -> 5.9738856 | P18: =BS!P26-BS!O26 -> 2.4693043
D19: =BS!D27 -> Accrued expenses | E19: =Currency&"'000" -> $'000 | G19: =AVERAGE(L19:P19) -> 3.660182 | L19: =BS!L27-BS!K27 -> 19.036986 | M19: =BS!M27-BS!L27 -> -2.9290411 | N19: =BS!N27-BS!M27 -> 0.34152756 | O19: =BS!O27-BS!N27 -> 1.115029 | P19: =BS!P27-BS!O27 -> 0.7364083
D20: =BS!D28 -> Other liabilities | E20: =Currency&"'000" -> $'000 | G20: =AVERAGE(L20:P20) -> 2.9281456 | L20: =BS!L28-BS!K28 -> 15.229589 | M20: =BS!M28-BS!L28 -> -2.3432329 | N20: =BS!N28-BS!M28 -> 0.27322205 | O20: =BS!O28-BS!N28 -> 0.89202317 | P20: =BS!P28-BS!O28 -> 0.58912664
D21: Taxation
D22: Tax paid | E22: =Currency&"'000" -> $'000 | G22: =AVERAGE(L22:P22) -> -27.764112 | L22: =-PL!K25 -> 0 | M22: =-PL!L25 -> -26.6847 | N22: =-PL!M25 -> -35.860029 | O22: =-PL!N25 -> -36.762681 | P22: =-PL!O25 -> -39.513151
D23: Net CFFO | E23: =Currency&"'000" -> $'000 | G23: =AVERAGE(L23:P23) -> 128.40388 | L23: =SUM(L11:L22) -> 61.457123 | M23: =SUM(M11:M22) -> 143.65063 | N23: =SUM(N11:N22) -> 141.7121 | O23: =SUM(O11:O22) -> 151.66808 | P23: =SUM(P11:P22) -> 143.53148
C24: Cash flow from Investing Activities (CFFI)
D25: PPE | E25: =Currency&"'000" -> $'000 | G25: =AVERAGE(L25:P25) -> -18.503322 | L25: =-Calc!L62/Div -> -53 | M25: =-Calc!M62/Div -> -5.4325 | N25: =-Calc!N62/Div -> -11.125763 | O25: =-Calc!O62/Div -> -11.371663 | P25: =-Calc!P62/Div -> -11.586683
D26: Net CFFI | E26: =Currency&"'000" -> $'000 | G26: =AVERAGE(L26:P26) -> -18.503322 | L26: =SUM(L25) -> -53 | M26: =SUM(M25) -> -5.4325 | N26: =SUM(N25) -> -11.125763 | O26: =SUM(O25) -> -11.371663 | P26: =SUM(P25) -> -11.586683
C27: Cash flow from Financing Activities (CFFF)
D28: Equity new issue | E28: =Currency&"'000" -> $'000 | G28: =AVERAGE(L28:P28) -> 30 | L28: =Calc!L36/Div -> 150 | M28: =Calc!M36/Div -> 0 | N28: =Calc!N36/Div -> 0 | O28: =Calc!O36/Div -> 0 | P28: =Calc!P36/Div -> 0
D29: Long term loans | E29: =Currency&"'000" -> $'000 | G29: =AVERAGE(L29:P29) -> 20 | L29: =Calc!L17/Div -> 100 | M29: =Calc!M17/Div -> 0 | N29: =Calc!N17/Div -> 0 | O29: =Calc!O17/Div -> 0 | P29: =Calc!P17/Div -> 0
D30: Dividends | E30: =Currency&"'000" -> $'000 | G30: =AVERAGE(L30:P30) -> -38.503392 | L30: =-Calc!L42/Div -> -27.96759 | M30: =-Calc!M42/Div -> -38.80525 | N30: =-Calc!N42/Div -> -40.34116 | O30: =-Calc!O42/Div -> -43.999495 | P30: =-Calc!P42/Div -> -41.403463
D31: Principal repayment | E31: =Currency&"'000" -> $'000 | G31: =AVERAGE(L31:P31) -> -20 | L31: =-Calc!L22/Div -> -22.46952 | M31: =-Calc!M22/Div -> -24.078338 | N31: =-Calc!N22/Div -> -25.802347 | O31: =-Calc!O22/Div -> -27.649795 | P31: =-Calc!P22/Div -> 0
D32: Net CFFF | E32: =Currency&"'000" -> $'000 | G32: =AVERAGE(L32:P32) -> -8.5033915 | L32: =SUM(L28:L31) -> 199.56289 | M32: =SUM(M28:M31) -> -62.883588 | N32: =SUM(N28:N31) -> -66.143506 | O32: =SUM(O28:O31) -> -71.64929 | P32: =SUM(P28:P31) -> -41.403463
C33: Cash Schedule
D34: Beginning balance | E34: =Currency&"'000" -> $'000 | G34: =AVERAGE(L34:P34) -> 313.90411 | L34: =K36 | M34: =L36 -> 208.02001 | N34: =M36 -> 283.35455 | O34: =N36 -> 347.79738 | P34: =O36 -> 416.44451
D35: Cash for the period | E35: =Currency&"'000" -> $'000 | G35: =AVERAGE(L35:P35) -> 101.39717 | L35: =L23+L26+L32 -> 208.02001 | M35: =M23+M26+M32 -> 75.334542 | N35: =N23+N26+N32 -> 64.442828 | O35: =O23+O26+O32 -> 68.647125 | P35: =P23+P26+P32 -> 90.541337
D36: Ending cash balance | E36: =Currency&"'000" -> $'000 | G36: =AVERAGE(L36:P36) -> 352.52046 | L36: =L34+L35 -> 208.02001 | M36: =M34+M35 -> 283.35455 | N36: =N34+N35 -> 347.79738 | O36: =O34+O35 -> 416.44451 | P36: =P34+P35 -> 506.98584

Sheet Analysis
B2: =Guide!$F$33 -> TOWV Bootcamp Limited
B3: Margin, Ratios & Analysis
G4: period start | L4: =K5+1 -> 44562 | M4: =L5+1 -> 44927 | N4: =M5+1 -> 45292 | O4: =N5+1 -> 45658 | P4: =O5+1 -> 46023
C5: =Scenario -> Live Scenario: Base Case | G5: Period end | K5: =Guide!F39-1 -> 44561 | L5: =EDATE(K5,Guide!$F$41) -> 44926 | M5: =EDATE(L5,Guide!$F$41) -> 45291 | N5: =EDATE(M5,Guide!$F$41) -> 45657 | O5: =EDATE(N5,Guide!$F$41) -> 46022 | P5: =EDATE(O5,Guide!$F$41) -> 46387
C6: Model balance check | G6: Years | L6: =YEAR(L4) -> 2022 | M6: =YEAR(M4) -> 2023 | N6: =YEAR(N4) -> 2024 | O6: =YEAR(O4) -> 2025 | P6: =YEAR(P4) -> 2026
D7: Descriptions | E7: unit | F7: Inputs/Linked | G7: Row Aver. | H7: Row Total
B9: Analysis
C10: Ratio & Metrics
D11: Revenue growth | L11: =PL!L11 -> 0 | M11: =PL!M11 -> 0.045 | N11: =PL!N11 -> 0.055 | O11: =PL!O11 -> 0.1005 | P11: =PL!P11 -> 0.025
D12: Gross profit margin | L12: =PL!L15 -> 0.45529294 | M12: =PL!M15 -> 0.44230027 | N12: =PL!N15 -> 0.42924912 | O12: =PL!O15 -> 0.41631483 | P12: =PL!P15 -> 0.40374441
D13: Opex to sales | L13: =PL!L17 -> 0.30841101 | M13: =PL!M17 -> 0.24972126 | N13: =PL!N17 -> 0.24238354 | O13: =PL!O17 -> 0.23453557 | P13: =PL!P17 -> 0.23840848
D14: EBITDA margin | L14: =PL!L19 -> 0.14688194 | M14: =PL!M19 -> 0.192579 | N14: =PL!N19 -> 0.18686558 | O14: =PL!O19 -> 0.18177926 | P14: =PL!P19 -> 0.16533593
D15: EBT margin | L15: =PL!L24/PL!L10 -> 0.13305593 | M15: =PL!M24/PL!M10 -> 0.17542889 | N15: =PL!N24/PL!N10 -> 0.17234476 | O15: =PL!O24/PL!O10 -> 0.17027414 | P15: =PL!P24/PL!P10 -> 0.15587787
D16: Net profit margin | L16: =PL!L26/PL!L10 -> 0.10344574 | M16: =PL!M26/PL!M10 -> 0.13735098 | N16: =PL!N26/PL!N10 -> 0.13534343 | O16: =PL!O26/PL!O10 -> 0.13413634 | P16: =PL!P26/PL!P10 -> 0.12314352
D17: ROE | L17: =PL!L26/AVERAGE(BS!K36:L36) -> 0.43308693 | M17: =PL!M26/AVERAGE(BS!L36:M36) -> 0.49649017 | N17: =PL!N26/AVERAGE(BS!M36:N36) -> 0.38107887 | O17: =PL!O26/AVERAGE(BS!N36:O36) -> 0.32500826 | P17: =PL!P26/AVERAGE(BS!O36:P36) -> 0.25051914
D18: ROI | L18: =PL!L26/(Inputs!$L$38/Div) -> 0.3729012 | M18: =PL!M26/(Inputs!$L$38/Div) -> 0.51740333 | N18: =PL!N26/(Inputs!$L$38/Div) -> 0.53788213 | O18: =PL!O26/(Inputs!$L$38/Div) -> 0.58665994 | P18: =PL!P26/(Inputs!$L$38/Div) -> 0.55204617
D19: ROA | L19: =PL!L22/AVERAGE(BS!K20:L20) -> 0.32244183 | M19: =PL!M22/AVERAGE(BS!L20:M20) -> 0.39649182 | N19: =PL!N22/AVERAGE(BS!M20:N20) -> 0.34744078 | O19: =PL!O22/AVERAGE(BS!N20:O20) -> 0.32256986 | P19: =PL!P22/AVERAGE(BS!O20:P20) -> 0.25882335
D21: {=INDEX(PL_Metrics,PL_switch)} -> Revenue growth | E21: 1 | L21: {=INDEX(L11:L19,PL_switch)} -> 0 | M21: {=INDEX(M11:M19,PL_switch)} -> 0.045 | N21: {=INDEX(N11:N19,PL_switch)} -> 0.055 | O21: {=INDEX(O11:O19,PL_switch)} -> 0.1005 | P21: {=INDEX(P11:P19,PL_switch)} -> 0.025
C24: Financial Summary
D25: =PL!D10 -> Revenue | L25: =PL!L10 -> 901.2 | M25: =PL!M10 -> 941.754 | N25: =PL!N10 -> 993.55047 | O25: =PL!O10 -> 1093.4023 | P25: =PL!P10 -> 1120.7374
D26: =PL!D12 -> Cost of Sales | L26: =PL!L12 -> 490.89 | M26: =PL!M12 -> 525.21596 | N26: =PL!N12 -> 567.0698 | O26: =PL!O12 -> 638.20271 | P26: =PL!P12 -> 668.24591
D27: =PL!D14 -> Gross Profit | L27: =PL!L14 -> 410.31 | M27: =PL!M14 -> 416.53805 | N27: =PL!N14 -> 426.48067 | O27: =PL!O14 -> 455.19959 | P27: =PL!P14 -> 452.49144
D28: =PL!D16 -> SG&A | L28: =PL!L16 -> 277.94 | M28: =PL!M16 -> 235.176 | N28: =PL!N16 -> 240.82028 | O28: =PL!O16 -> 256.44173 | P28: =PL!P16 -> 267.19329
D29: =PL!D18 -> EBITDA | L29: =PL!L18 -> 132.37 | M29: =PL!M18 -> 181.36204 | N29: =PL!N18 -> 185.66039 | O29: =PL!O18 -> 198.75786 | P29: =PL!P18 -> 185.29815
D30: =PL!D24 -> EBT | L30: =PL!L24 -> 119.91 | M30: =PL!M24 -> 165.21086 | N30: =PL!N24 -> 171.23321 | O30: =PL!O24 -> 186.17814 | P30: =PL!P24 -> 174.69815
D31: =PL!D26 -> Net profit | L31: =PL!L26 -> 93.2253 | M31: =PL!M26 -> 129.35083 | N31: =PL!N26 -> 134.47053 | O31: =PL!O26 -> 146.66498 | P31: =PL!P26 -> 138.01154
D32: Total Asset | L32: =BS!L20 -> 394.08659 | M32: =BS!M20 -> 467.2782 | N32: =BS!N20 -> 540.43532 | O32: =BS!O20 -> 626.18243 | P32: =BS!P20 -> 723.75881
D33: Total Liabilities | L33: =BS!L31 -> 178.82888 | M33: =BS!M31 -> 161.47491 | N33: =BS!N31 -> 140.50266 | O33: =BS!O31 -> 123.58427 | P33: =BS!P31 -> 124.55257
D34: Total Equity | L34: =BS!L36 -> 215.25771 | M34: =BS!M36 -> 305.80329 | N34: =BS!N36 -> 399.93267 | O34: =BS!O36 -> 502.59815 | P34: =BS!P36 -> 599.20623
D35: CFFO | L35: =CF!L23 -> 61.457123 | M35: =CF!M23 -> 143.65063 | N35: =CF!N23 -> 141.7121 | O35: =CF!O23 -> 151.66808 | P35: =CF!P23 -> 143.53148
D36: Cash balance | L36: =CF!L36 -> 208.02001 | M36: =CF!M36 -> 283.35455 | N36: =CF!N36 -> 347.79738 | O36: =CF!O36 -> 416.44451 | P36: =CF!P36 -> 506.98584
D38: {=INDEX(F_List,F_Switch1)} -> Revenue | F38: 1 | L38: {=INDEX(L25:L36,F_Switch1)} -> 901.2 | M38: {=INDEX(M25:M36,F_Switch1)} -> 941.754 | N38: {=INDEX(N25:N36,F_Switch1)} -> 993.55047 | O38: {=INDEX(O25:O36,F_Switch1)} -> 1093.4023 | P38: {=INDEX(P25:P36,F_Switch1)} -> 1120.7374
D39: {=INDEX(F_List,F_Switch2)} -> EBITDA | F39: 5 | L39: {=INDEX(L25:L36,F_Switch2)} -> 132.37 | M39: {=INDEX(M25:M36,F_Switch2)} -> 181.36204 | N39: {=INDEX(N25:N36,F_Switch2)} -> 185.66039 | O39: {=INDEX(O25:O36,F_Switch2)} -> 198.75786 | P39: {=INDEX(P25:P36,F_Switch2)} -> 185.29815
C42: Free cash flow from firm (FCFF)
D43: Assumptions Linked
D44: =Inputs!D27 -> Provision for tax | E44: =Inputs!E27 -> %age | L44: =Inputs!L27 -> 0.21 | M44: =Inputs!M27 -> 0.21 | N44: =Inputs!N27 -> 0.21 | O44: =Inputs!O27 -> 0.21 | P44: =Inputs!P27 -> 0.21
D46: EBIT | E46: =Currency&"'000" -> $'000 | L46: =PL!L22 -> 127.07 | M46: =PL!M22 -> 170.76205 | N46: =PL!N22 -> 175.06039 | O46: =PL!O22 -> 188.15786 | P46: =PL!P22 -> 174.69815
D47: Less: tax | E47: =Currency&"'000" -> $'000 | L47: =L46*L44 -> 26.6847 | M47: =M46*M44 -> 35.860029 | N47: =N46*N44 -> 36.762681 | O47: =O46*O44 -> 39.513151 | P47: =P46*P44 -> 36.686612
D48: NOPAT | E48: =Currency&"'000" -> $'000 | L48: =L46-L47 -> 100.3853 | M48: =M46-M47 -> 134.90202 | N48: =N46-N47 -> 138.29771 | O48: =O46-O47 -> 148.64471 | P48: =P46-P47 -> 138.01154
D49: Add: Depreciation | E49: =Currency&"'000" -> $'000 | L49: =PL!L20 -> 5.3 | M49: =PL!M20 -> 10.6 | N49: =PL!N20 -> 10.6 | O49: =PL!O20 -> 10.6 | P49: =PL!P20 -> 10.6
D50: Less: capex | E50: =Currency&"'000" -> $'000 | L50: =-CF!L25 -> 53 | M50: =-CF!M25 -> 5.4325 | N50: =-CF!N25 -> 11.125763 | O50: =-CF!O25 -> 11.371663 | P50: =-CF!P25 -> 11.586683
D51: Less: change in OWC | E51: =Currency&"'000" -> $'000 | L51: =SUM(CF!L15:L20) -> -63.752877 | M51: =SUM(CF!M15:M20) -> -5.475533 | N51: =SUM(CF!N15:N20) -> -4.2610863 | O51: =SUM(CF!O15:O20) -> -8.3473765 | P51: =SUM(CF!P15:P20) -> -2.2535207
D52: FCFF | E52: =Currency&"'000" -> $'000 | L52: =L48+L49-L50-L51 -> 116.43818 | M52: =M48+M49-M50-M51 -> 145.54505 | N52: =N48+N49-N50-N51 -> 142.03303 | O52: =O48+O49-O50-O51 -> 156.22042 | P52: =P48+P49-P50-P51 -> 139.27838
L54: =K54+1 -> 1 | M54: =L54+1 -> 2 | N54: =M54+1 -> 3 | O54: =N54+1 -> 4 | P54: =O54+1 -> 5
D55: Discounting rate | E55: %age | L55: =$F$76 -> 0.0642926 | M55: =$F$76 -> 0.0642926 | N55: =$F$76 -> 0.0642926 | O55: =$F$76 -> 0.0642926 | P55: =$F$76 -> 0.0642926
D56: Discounting factor | E56: factor | L56: =(1+L55)^-L54 -> 0.93959124 | M56: =(1+M55)^-M54 -> 0.88283169 | N56: =(1+N55)^-N54 -> 0.82950092 | O56: =(1+O55)^-O54 -> 0.7793918 | P56: =(1+P55)^-P54 -> 0.7323097
D57: FCCF | L57: =L52*L56 -> 109.40429 | M57: =M52*M56 -> 128.49178 | N57: =N52*N56 -> 117.81653 | O57: =O52*O56 -> 121.75692 | P57: =P52*P56 -> 101.99491
D58: NPV of Explicit period | H58: =SUM(L57:P57) -> 579.46443
C60: Discounting Factor
D61: Financing
D62: Loans | E62: =Currency&"'000" -> $'000 | F62: =Inputs!L35 -> 100000 | G62: =F62/$F$64 -> 0.4
D63: Equity | E63: =Currency&"'000" -> $'000 | F63: =Inputs!L37 -> 150000 | G63: =F63/$F$64 -> 0.6
F64: =SUM(F62:F63) -> 250000 | G64: =SUM(G62:G63) -> 1
D66: Cost of Equity | F66: (RF+Beta x Mp)
D67: Risk Free rate | E67: %age | F67: 0.0145 | G67: https://www.statista.com/statistics/1058454/yield-curve-usa/
D68: Market premium | E68: %age | F68: 0.0555 | G68: https://www.statista.com/statistics/664840/average-market-risk-premium-usa/#:~:text=The%20average%20market%20risk%20premium,and%205.7%20percent%20since%202011.
D69: Beta | E69: %age | F69: 0.99 | G69: http://pages.stern.nyu.edu/~adamodar/New_Home_Page/datafile/wacc.html
D70: Cost of Equity | E70: %age | F70: =F67+F69*F68 -> 0.069445
D72: Cost of Debt | E72: %age | F72: =Inputs!L43 -> 0.0716
D73: Tax rate | E73: %age | F73: =L44 -> 0.21
D74: Cost after tax | E74: %age | F74: =(1-F73)*F72 -> 0.056564
D76: WACC | F76: =(F70*G63)+(F74*G62) -> 0.0642926
C78: Net Present Value | K78: 0 | L78: =K78+1 -> 1 | M78: =L78+1 -> 2 | N78: =M78+1 -> 3 | O78: =N78+1 -> 4 | P78: =O78+1 -> 5
D79: Cash Flow | E79: =Currency&"'000" -> $'000 | K79: =-Inputs!L38/Div -> -250 | L79: =L52 -> 116.43818 | M79: =M52 -> 145.54505 | N79: =N52 -> 142.03303 | O79: =O52 -> 156.22042 | P79: =P52 -> 139.27838
D80: Discount Rate | E80: %age | K80: =$F$76 -> 0.0642926 | L80: =$F$76 -> 0.0642926 | M80: =$F$76 -> 0.0642926 | N80: =$F$76 -> 0.0642926 | O80: =$F$76 -> 0.0642926 | P80: =$F$76 -> 0.0642926
D81: Discount factor | E81: factor | K81: =(1+K80)^-K78 -> 1 | L81: =(1+L80)^-L78 -> 0.93959124 | M81: =(1+M80)^-M78 -> 0.88283169 | N81: =(1+N80)^-N78 -> 0.82950092 | O81: =(1+O80)^-O78 -> 0.7793918 | P81: =(1+P80)^-P78 -> 0.7323097
D82: Present value | E82: =Currency&"'000" -> $'000 | K82: =K79*K81 -> -250 | L82: =L79*L81 -> 109.40429 | M82: =M79*M81 -> 128.49178 | N82: =N79*N81 -> 117.81653 | O82: =O79*O81 -> 121.75692 | P82: =P79*P81 -> 101.99491
D83: Net Present value (calc) | E83: =Currency&"'000" -> $'000 | H83: =SUM(K82:P82) -> 329.46443
D84: Net Present value (excel) | E84: =Currency&"'000" -> $'000 | H84: {=NPV(F76,L79:P79)+K79} -> 329.46443
C86: Payback Period
D87: Cash flow | E87: =Currency&"'000" -> $'000 | K87: =K79 -> -250 | L87: =L79 -> 116.43818 | M87: =M79 -> 145.54505 | N87: =N79 -> 142.03303 | O87: =O79 -> 156.22042 | P87: =P79 -> 139.27838
D88: Cummulative cash flow | E88: =Currency&"'000" -> $'000 | K88: =SUM($K$87:K87) -> -250 | L88: =SUM($K$87:L87) -> -133.56182 | M88: =SUM($K$87:M87) -> 11.983225 | N88: =SUM($K$87:N87) -> 154.01625 | O88: =SUM($K$87:O87) -> 310.23668 | P88: =SUM($K$87:P87) -> 449.51506
D89: Payback period | E89: =Currency&"'000" -> $'000 | F89: =SUM(L89:P89) -> 1.9176666 | H89: formula 1 | L89: =IF(L88<0,1,IF(K88<0,ABS(K88/L87),"")) -> 1 | M89: =IF(M88<0,1,IF(L88<0,ABS(L88/M87),"")) -> 0.91766655 | N89: =IF(N88<0,1,IF(M88<0,ABS(M88/N87),"")) | O89: =IF(O88<0,1,IF(N88<0,ABS(N88/O87),"")) | P89: =IF(P88<0,1,IF(O88<0,ABS(O88/P87),""))
D90: Payback period | E90: years | F90: =SUM(L90:P90) -> 1.9176666 | H90: formula 2 | L90: =IF(AND(K88<0,L88>0),K78+ABS(K88/L87),"") | M90: =IF(AND(L88<0,M88>0),L78+ABS(L88/M87),"") -> 1.9176666 | N90: =IF(AND(M88<0,N88>0),M78+ABS(M88/N87),"") | O90: =IF(AND(N88<0,O88>0),N78+ABS(N88/O87),"") | P90: =IF(AND(O88<0,P88>0),O78+ABS(O88/P87),"")
C92: Discounted Payback Period
D93: PV Cash | E93: =Currency&"'000" -> $'000 | K93: =K82 -> -250 | L93: =L82 -> 109.40429 | M93: =M82 -> 128.49178 | N93: =N82 -> 117.81653 | O93: =O82 -> 121.75692 | P93: =P82 -> 101.99491
D94: Cummulative | E94: =Currency&"'000" -> $'000 | K94: =SUM($K$93:K93) -> -250 | L94: =SUM($K$93:L93) -> -140.59571 | M94: =SUM($K$93:M93) -> -12.103928 | N94: =SUM($K$93:N93) -> 105.7126 | O94: =SUM($K$93:O93) -> 227.46952 | P94: =SUM($K$93:P93) -> 329.46443
D95: Payback period | E95: year | F95: =SUM(L95:P95) -> 3.1027354 | L95: =IF(AND(K94<0,L94>0),L78+ABS(K94/L93),"") | M95: =IF(AND(L94<0,M94>0),M78+ABS(L94/M93),"") | N95: =IF(AND(M94<0,N94>0),N78+ABS(M94/N93),"") -> 3.1027354 | O95: =IF(AND(N94<0,O94>0),O78+ABS(N94/O93),"") | P95: =IF(AND(O94<0,P94>0),P78+ABS(O94/P93),"")
C97: Internal Rate of Return
D98: =D79 -> Cash Flow | E98: =E79 -> $'000 | K98: =K79 -> -250 | L98: =L79 -> 116.43818 | M98: =M79 -> 145.54505 | N98: =N79 -> 142.03303 | O98: =O79 -> 156.22042 | P98: =P79 -> 139.27838
D99: IRR | E99: =E80 -> %age | F99: =IRR(K98:P98,F76) -> 0.45767233
C101: Terminal Value at Perpectual growth
D102: FCFF x (1 + growth rate)/Wacc - growth rate)
D103: FCFF | E103: =Currency&"'000" -> $'000 | F103: =P52 -> 139.27838
D104: g | F104: 0.025
D105: WACC | F105: =F76 -> 0.0642926
D106: Terminal value | E106: =Currency&"'000" -> $'000 | F106: =F103*(1+F104)/(F105-F104) -> 3633.2627
D107: NPV of TV | E107: =Currency&"'000" -> $'000 | F107: {=NPV(F105,F106)} -> 3413.7818
C109: DCF Schedule
D110: NPV of explicit period | E110: =Currency&"'000" -> $'000 | F110: =H58 -> 579.46443
D111: NPV of TV | E111: =Currency&"'000" -> $'000 | F111: =F107 -> 3413.7818
D112: Enterprise value | E112: =Currency&"'000" -> $'000 | F112: =SUM(F110:F111) -> 3993.2462 | H112: =F112 -> 3993.2462
D113: Add cash | E113: =Currency&"'000" -> $'000 | F113: 0
D114: Less debt | E114: =Currency&"'000" -> $'000 | F114: =Inputs!L35/Div -> 100
D115: Equity Value | E115: =Currency&"'000" -> $'000 | F115: =F112+F113-F114 -> 3893.2462
C117: Percentage Offer
D118: Investment offer | F118: 150
D119: value | F119: =F112 -> 3993.2462
D120: Percentage offer | F120: =F118/(F118+F119) -> 0.036203496
